[{"fips":"51179","date":"2021-06-17","county":"Stafford","state":"Virginia","cases":11469,"deaths":82},{"fips":"51179","date":"2021-03-02","county":"Stafford","state":"Virginia","cases":9620,"deaths":68},{"fips":"51179","date":"2021-03-03","county":"Stafford","state":"Virginia","cases":9644,"deaths":68},{"fips":"51179","date":"2021-03-04","county":"Stafford","state":"Virginia","cases":9653,"deaths":68},{"fips":"51179","date":"2021-03-05","county":"Stafford","state":"Virginia","cases":9649,"deaths":68},{"fips":"51179","date":"2021-03-06","county":"Stafford","state":"Virginia","cases":9659,"deaths":68},{"fips":"51179","date":"2021-03-07","county":"Stafford","state":"Virginia","cases":9671,"deaths":68},{"fips":"51179","date":"2021-03-08","county":"Stafford","state":"Virginia","cases":9687,"deaths":68},{"fips":"51179","date":"2021-03-09","county":"Stafford","state":"Virginia","cases":9715,"deaths":69},{"fips":"51179","date":"2021-03-10","county":"Stafford","state":"Virginia","cases":9736,"deaths":68},{"fips":"51179","date":"2021-03-11","county":"Stafford","state":"Virginia","cases":9754,"deaths":69},{"fips":"51179","date":"2021-03-12","county":"Stafford","state":"Virginia","cases":9778,"deaths":69},{"fips":"51179","date":"2021-03-13","county":"Stafford","state":"Virginia","cases":9802,"deaths":69},{"fips":"51179","date":"2021-03-14","county":"Stafford","state":"Virginia","cases":9828,"deaths":70},{"fips":"51179","date":"2021-03-15","county":"Stafford","state":"Virginia","cases":9843,"deaths":70},{"fips":"51179","date":"2021-03-16","county":"Stafford","state":"Virginia","cases":9837,"deaths":69},{"fips":"51179","date":"2021-03-17","county":"Stafford","state":"Virginia","cases":9858,"deaths":69},{"fips":"51179","date":"2021-03-18","county":"Stafford","state":"Virginia","cases":9876,"deaths":69},{"fips":"51179","date":"2021-03-19","county":"Stafford","state":"Virginia","cases":9891,"deaths":68},{"fips":"51179","date":"2021-03-20","county":"Stafford","state":"Virginia","cases":9915,"deaths":68},{"fips":"51179","date":"2021-03-21","county":"Stafford","state":"Virginia","cases":9928,"deaths":68},{"fips":"51179","date":"2021-03-22","county":"Stafford","state":"Virginia","cases":9947,"deaths":68},{"fips":"51179","date":"2021-03-23","county":"Stafford","state":"Virginia","cases":9970,"deaths":68},{"fips":"51179","date":"2021-03-24","county":"Stafford","state":"Virginia","cases":9998,"deaths":68},{"fips":"51179","date":"2021-03-25","county":"Stafford","state":"Virginia","cases":10036,"deaths":68},{"fips":"51179","date":"2021-03-26","county":"Stafford","state":"Virginia","cases":10059,"deaths":68},{"fips":"51179","date":"2021-03-27","county":"Stafford","state":"Virginia","cases":10081,"deaths":68},{"fips":"51179","date":"2021-03-28","county":"Stafford","state":"Virginia","cases":10093,"deaths":68},{"fips":"51179","date":"2021-03-29","county":"Stafford","state":"Virginia","cases":10109,"deaths":69},{"fips":"51179","date":"2021-03-30","county":"Stafford","state":"Virginia","cases":10132,"deaths":69},{"fips":"51179","date":"2021-03-31","county":"Stafford","state":"Virginia","cases":10150,"deaths":69},{"fips":"51179","date":"2021-04-01","county":"Stafford","state":"Virginia","cases":10197,"deaths":69},{"fips":"51179","date":"2021-04-02","county":"Stafford","state":"Virginia","cases":10241,"deaths":69},{"fips":"51179","date":"2021-04-03","county":"Stafford","state":"Virginia","cases":10264,"deaths":69},{"fips":"51179","date":"2021-04-04","county":"Stafford","state":"Virginia","cases":10284,"deaths":70},{"fips":"51179","date":"2021-04-05","county":"Stafford","state":"Virginia","cases":10299,"deaths":70},{"fips":"51179","date":"2021-04-06","county":"Stafford","state":"Virginia","cases":10332,"deaths":70},{"fips":"51179","date":"2021-04-07","county":"Stafford","state":"Virginia","cases":10359,"deaths":71},{"fips":"51179","date":"2021-04-08","county":"Stafford","state":"Virginia","cases":10393,"deaths":71},{"fips":"51179","date":"2021-04-09","county":"Stafford","state":"Virginia","cases":10418,"deaths":71},{"fips":"51179","date":"2021-04-10","county":"Stafford","state":"Virginia","cases":10454,"deaths":71},{"fips":"51179","date":"2021-04-11","county":"Stafford","state":"Virginia","cases":10476,"deaths":71},{"fips":"51179","date":"2021-04-12","county":"Stafford","state":"Virginia","cases":10519,"deaths":71},{"fips":"51179","date":"2021-04-13","county":"Stafford","state":"Virginia","cases":10560,"deaths":72},{"fips":"51179","date":"2021-04-14","county":"Stafford","state":"Virginia","cases":10599,"deaths":72},{"fips":"51179","date":"2021-04-15","county":"Stafford","state":"Virginia","cases":10630,"deaths":72},{"fips":"51179","date":"2021-04-16","county":"Stafford","state":"Virginia","cases":10658,"deaths":72},{"fips":"51179","date":"2021-04-17","county":"Stafford","state":"Virginia","cases":10705,"deaths":72},{"fips":"51179","date":"2021-04-18","county":"Stafford","state":"Virginia","cases":10739,"deaths":72},{"fips":"51179","date":"2021-04-19","county":"Stafford","state":"Virginia","cases":10754,"deaths":72},{"fips":"51179","date":"2021-04-20","county":"Stafford","state":"Virginia","cases":10789,"deaths":72},{"fips":"51179","date":"2021-04-21","county":"Stafford","state":"Virginia","cases":10831,"deaths":72},{"fips":"51179","date":"2021-04-22","county":"Stafford","state":"Virginia","cases":10867,"deaths":73},{"fips":"51179","date":"2021-04-23","county":"Stafford","state":"Virginia","cases":10906,"deaths":74},{"fips":"51179","date":"2021-04-24","county":"Stafford","state":"Virginia","cases":10922,"deaths":74},{"fips":"51179","date":"2021-04-25","county":"Stafford","state":"Virginia","cases":10946,"deaths":74},{"fips":"51179","date":"2021-04-26","county":"Stafford","state":"Virginia","cases":10958,"deaths":74},{"fips":"51179","date":"2021-04-27","county":"Stafford","state":"Virginia","cases":10979,"deaths":74},{"fips":"51179","date":"2021-04-28","county":"Stafford","state":"Virginia","cases":11007,"deaths":75},{"fips":"51179","date":"2021-04-29","county":"Stafford","state":"Virginia","cases":11031,"deaths":75},{"fips":"51179","date":"2021-04-30","county":"Stafford","state":"Virginia","cases":11067,"deaths":75},{"fips":"51179","date":"2021-05-01","county":"Stafford","state":"Virginia","cases":11092,"deaths":75},{"fips":"51179","date":"2021-05-02","county":"Stafford","state":"Virginia","cases":11106,"deaths":75},{"fips":"51179","date":"2021-05-03","county":"Stafford","state":"Virginia","cases":11113,"deaths":76},{"fips":"51179","date":"2021-05-04","county":"Stafford","state":"Virginia","cases":11133,"deaths":76},{"fips":"51179","date":"2021-05-05","county":"Stafford","state":"Virginia","cases":11155,"deaths":78},{"fips":"51179","date":"2021-05-06","county":"Stafford","state":"Virginia","cases":11178,"deaths":78},{"fips":"51179","date":"2021-05-07","county":"Stafford","state":"Virginia","cases":11195,"deaths":78},{"fips":"51179","date":"2021-05-08","county":"Stafford","state":"Virginia","cases":11208,"deaths":78},{"fips":"51179","date":"2021-05-09","county":"Stafford","state":"Virginia","cases":11221,"deaths":79},{"fips":"51179","date":"2021-05-10","county":"Stafford","state":"Virginia","cases":11230,"deaths":79},{"fips":"51179","date":"2021-05-11","county":"Stafford","state":"Virginia","cases":11239,"deaths":79},{"fips":"51179","date":"2021-05-12","county":"Stafford","state":"Virginia","cases":11244,"deaths":79},{"fips":"51179","date":"2021-05-13","county":"Stafford","state":"Virginia","cases":11265,"deaths":79},{"fips":"51179","date":"2021-05-14","county":"Stafford","state":"Virginia","cases":11275,"deaths":79},{"fips":"51179","date":"2021-05-15","county":"Stafford","state":"Virginia","cases":11295,"deaths":79},{"fips":"51179","date":"2021-05-16","county":"Stafford","state":"Virginia","cases":11304,"deaths":79},{"fips":"51179","date":"2021-05-17","county":"Stafford","state":"Virginia","cases":11309,"deaths":79},{"fips":"51179","date":"2021-05-18","county":"Stafford","state":"Virginia","cases":11317,"deaths":79},{"fips":"51179","date":"2021-05-19","county":"Stafford","state":"Virginia","cases":11327,"deaths":79},{"fips":"51179","date":"2021-05-20","county":"Stafford","state":"Virginia","cases":11345,"deaths":79},{"fips":"51179","date":"2021-05-21","county":"Stafford","state":"Virginia","cases":11361,"deaths":79},{"fips":"51179","date":"2021-05-22","county":"Stafford","state":"Virginia","cases":11373,"deaths":79},{"fips":"51179","date":"2021-05-23","county":"Stafford","state":"Virginia","cases":11377,"deaths":79},{"fips":"51179","date":"2021-05-24","county":"Stafford","state":"Virginia","cases":11378,"deaths":79},{"fips":"51179","date":"2021-05-25","county":"Stafford","state":"Virginia","cases":11389,"deaths":79},{"fips":"51179","date":"2021-05-26","county":"Stafford","state":"Virginia","cases":11393,"deaths":79},{"fips":"51179","date":"2021-05-27","county":"Stafford","state":"Virginia","cases":11402,"deaths":79},{"fips":"51179","date":"2021-05-28","county":"Stafford","state":"Virginia","cases":11400,"deaths":79},{"fips":"51179","date":"2021-05-29","county":"Stafford","state":"Virginia","cases":11401,"deaths":79},{"fips":"51179","date":"2021-05-30","county":"Stafford","state":"Virginia","cases":11408,"deaths":80},{"fips":"51179","date":"2021-05-31","county":"Stafford","state":"Virginia","cases":11414,"deaths":80},{"fips":"51179","date":"2021-06-01","county":"Stafford","state":"Virginia","cases":11417,"deaths":80},{"fips":"51179","date":"2021-06-02","county":"Stafford","state":"Virginia","cases":11428,"deaths":81},{"fips":"51179","date":"2021-06-03","county":"Stafford","state":"Virginia","cases":11435,"deaths":81},{"fips":"51179","date":"2021-06-04","county":"Stafford","state":"Virginia","cases":11433,"deaths":81},{"fips":"51179","date":"2021-06-05","county":"Stafford","state":"Virginia","cases":11444,"deaths":81},{"fips":"51179","date":"2021-06-06","county":"Stafford","state":"Virginia","cases":11451,"deaths":81},{"fips":"51179","date":"2021-06-07","county":"Stafford","state":"Virginia","cases":11453,"deaths":81},{"fips":"51179","date":"2021-06-08","county":"Stafford","state":"Virginia","cases":11456,"deaths":81},{"fips":"51179","date":"2021-06-09","county":"Stafford","state":"Virginia","cases":11460,"deaths":81},{"fips":"51179","date":"2021-06-10","county":"Stafford","state":"Virginia","cases":11460,"deaths":81},{"fips":"51179","date":"2021-06-11","county":"Stafford","state":"Virginia","cases":11458,"deaths":82},{"fips":"51179","date":"2021-06-12","county":"Stafford","state":"Virginia","cases":11460,"deaths":82},{"fips":"51179","date":"2021-06-13","county":"Stafford","state":"Virginia","cases":11458,"deaths":82},{"fips":"51179","date":"2021-06-14","county":"Stafford","state":"Virginia","cases":11459,"deaths":82},{"fips":"51179","date":"2021-06-15","county":"Stafford","state":"Virginia","cases":11462,"deaths":82},{"fips":"51179","date":"2021-06-16","county":"Stafford","state":"Virginia","cases":11467,"deaths":82},{"fips":"51179","date":"2021-01-19","county":"Stafford","state":"Virginia","cases":6887,"deaths":35},{"fips":"51179","date":"2021-01-22","county":"Stafford","state":"Virginia","cases":7080,"deaths":41},{"fips":"51179","date":"2021-01-23","county":"Stafford","state":"Virginia","cases":7169,"deaths":42},{"fips":"51179","date":"2021-01-24","county":"Stafford","state":"Virginia","cases":7210,"deaths":42},{"fips":"51179","date":"2021-01-25","county":"Stafford","state":"Virginia","cases":7341,"deaths":42},{"fips":"51179","date":"2021-01-26","county":"Stafford","state":"Virginia","cases":7489,"deaths":44},{"fips":"51179","date":"2021-01-27","county":"Stafford","state":"Virginia","cases":7586,"deaths":45},{"fips":"51179","date":"2021-01-28","county":"Stafford","state":"Virginia","cases":7687,"deaths":46},{"fips":"51179","date":"2021-01-29","county":"Stafford","state":"Virginia","cases":7766,"deaths":46},{"fips":"51179","date":"2021-01-30","county":"Stafford","state":"Virginia","cases":7909,"deaths":48},{"fips":"51179","date":"2021-01-31","county":"Stafford","state":"Virginia","cases":7956,"deaths":48},{"fips":"51179","date":"2021-02-01","county":"Stafford","state":"Virginia","cases":8005,"deaths":48},{"fips":"51179","date":"2021-02-02","county":"Stafford","state":"Virginia","cases":8058,"deaths":50},{"fips":"51179","date":"2021-02-03","county":"Stafford","state":"Virginia","cases":8123,"deaths":50},{"fips":"51179","date":"2021-02-04","county":"Stafford","state":"Virginia","cases":8183,"deaths":50},{"fips":"51179","date":"2021-02-05","county":"Stafford","state":"Virginia","cases":8299,"deaths":51},{"fips":"51179","date":"2021-02-06","county":"Stafford","state":"Virginia","cases":8490,"deaths":52},{"fips":"51179","date":"2021-02-07","county":"Stafford","state":"Virginia","cases":8525,"deaths":52},{"fips":"51179","date":"2021-02-08","county":"Stafford","state":"Virginia","cases":8554,"deaths":52},{"fips":"51179","date":"2021-02-09","county":"Stafford","state":"Virginia","cases":8623,"deaths":53},{"fips":"51179","date":"2021-02-10","county":"Stafford","state":"Virginia","cases":8727,"deaths":53},{"fips":"51179","date":"2021-02-11","county":"Stafford","state":"Virginia","cases":8839,"deaths":53},{"fips":"51179","date":"2021-02-12","county":"Stafford","state":"Virginia","cases":9015,"deaths":54},{"fips":"51179","date":"2021-02-13","county":"Stafford","state":"Virginia","cases":9061,"deaths":54},{"fips":"51179","date":"2021-02-14","county":"Stafford","state":"Virginia","cases":9140,"deaths":54},{"fips":"51179","date":"2021-02-15","county":"Stafford","state":"Virginia","cases":9159,"deaths":54},{"fips":"51179","date":"2021-02-16","county":"Stafford","state":"Virginia","cases":9199,"deaths":54},{"fips":"51179","date":"2021-02-17","county":"Stafford","state":"Virginia","cases":9252,"deaths":54},{"fips":"51179","date":"2021-02-18","county":"Stafford","state":"Virginia","cases":9290,"deaths":55},{"fips":"51179","date":"2021-02-19","county":"Stafford","state":"Virginia","cases":9312,"deaths":55},{"fips":"51179","date":"2021-02-20","county":"Stafford","state":"Virginia","cases":9320,"deaths":55},{"fips":"51179","date":"2021-02-21","county":"Stafford","state":"Virginia","cases":9333,"deaths":58},{"fips":"51179","date":"2021-02-22","county":"Stafford","state":"Virginia","cases":9341,"deaths":61},{"fips":"51179","date":"2021-02-23","county":"Stafford","state":"Virginia","cases":9368,"deaths":64},{"fips":"51179","date":"2021-02-24","county":"Stafford","state":"Virginia","cases":9418,"deaths":65},{"fips":"51179","date":"2021-02-25","county":"Stafford","state":"Virginia","cases":9448,"deaths":65},{"fips":"51179","date":"2021-02-26","county":"Stafford","state":"Virginia","cases":9479,"deaths":66},{"fips":"51179","date":"2021-02-27","county":"Stafford","state":"Virginia","cases":9491,"deaths":66},{"fips":"51179","date":"2021-02-28","county":"Stafford","state":"Virginia","cases":9555,"deaths":67},{"fips":"51179","date":"2021-03-01","county":"Stafford","state":"Virginia","cases":9582,"deaths":67},{"fips":"51179","date":"2020-03-26","county":"Stafford","state":"Virginia","cases":11,"deaths":0},{"fips":"51179","date":"2020-03-27","county":"Stafford","state":"Virginia","cases":11,"deaths":0},{"fips":"51179","date":"2020-03-28","county":"Stafford","state":"Virginia","cases":11,"deaths":0},{"fips":"51179","date":"2020-03-29","county":"Stafford","state":"Virginia","cases":13,"deaths":0},{"fips":"51179","date":"2020-03-30","county":"Stafford","state":"Virginia","cases":20,"deaths":0},{"fips":"51179","date":"2020-03-31","county":"Stafford","state":"Virginia","cases":24,"deaths":0},{"fips":"51179","date":"2020-04-01","county":"Stafford","state":"Virginia","cases":28,"deaths":0},{"fips":"51179","date":"2020-04-02","county":"Stafford","state":"Virginia","cases":28,"deaths":0},{"fips":"51179","date":"2020-04-03","county":"Stafford","state":"Virginia","cases":29,"deaths":0},{"fips":"51179","date":"2020-04-04","county":"Stafford","state":"Virginia","cases":38,"deaths":0},{"fips":"51179","date":"2020-04-05","county":"Stafford","state":"Virginia","cases":41,"deaths":0},{"fips":"51179","date":"2020-04-06","county":"Stafford","state":"Virginia","cases":43,"deaths":0},{"fips":"51179","date":"2020-04-07","county":"Stafford","state":"Virginia","cases":49,"deaths":0},{"fips":"51179","date":"2020-04-08","county":"Stafford","state":"Virginia","cases":48,"deaths":0},{"fips":"51179","date":"2020-04-09","county":"Stafford","state":"Virginia","cases":54,"deaths":0},{"fips":"51179","date":"2020-04-10","county":"Stafford","state":"Virginia","cases":60,"deaths":0},{"fips":"51179","date":"2020-04-11","county":"Stafford","state":"Virginia","cases":67,"deaths":0},{"fips":"51179","date":"2020-04-12","county":"Stafford","state":"Virginia","cases":72,"deaths":1},{"fips":"51179","date":"2020-04-13","county":"Stafford","state":"Virginia","cases":87,"deaths":1},{"fips":"51179","date":"2020-04-14","county":"Stafford","state":"Virginia","cases":95,"deaths":1},{"fips":"51179","date":"2020-04-15","county":"Stafford","state":"Virginia","cases":108,"deaths":1},{"fips":"51179","date":"2020-04-16","county":"Stafford","state":"Virginia","cases":120,"deaths":1},{"fips":"51179","date":"2020-04-17","county":"Stafford","state":"Virginia","cases":128,"deaths":1},{"fips":"51179","date":"2020-04-18","county":"Stafford","state":"Virginia","cases":143,"deaths":1},{"fips":"51179","date":"2020-04-19","county":"Stafford","state":"Virginia","cases":152,"deaths":1},{"fips":"51179","date":"2020-04-20","county":"Stafford","state":"Virginia","cases":161,"deaths":1},{"fips":"51179","date":"2020-04-21","county":"Stafford","state":"Virginia","cases":164,"deaths":2},{"fips":"51179","date":"2020-04-22","county":"Stafford","state":"Virginia","cases":170,"deaths":2},{"fips":"51179","date":"2020-04-23","county":"Stafford","state":"Virginia","cases":180,"deaths":2},{"fips":"51179","date":"2020-04-24","county":"Stafford","state":"Virginia","cases":193,"deaths":2},{"fips":"51179","date":"2020-04-25","county":"Stafford","state":"Virginia","cases":198,"deaths":2},{"fips":"51179","date":"2020-04-26","county":"Stafford","state":"Virginia","cases":213,"deaths":2},{"fips":"51179","date":"2020-04-27","county":"Stafford","state":"Virginia","cases":218,"deaths":2},{"fips":"51179","date":"2020-04-28","county":"Stafford","state":"Virginia","cases":221,"deaths":2},{"fips":"51179","date":"2020-04-29","county":"Stafford","state":"Virginia","cases":225,"deaths":2},{"fips":"51179","date":"2020-04-30","county":"Stafford","state":"Virginia","cases":240,"deaths":2},{"fips":"51179","date":"2020-05-01","county":"Stafford","state":"Virginia","cases":251,"deaths":2},{"fips":"51179","date":"2020-05-02","county":"Stafford","state":"Virginia","cases":262,"deaths":2},{"fips":"51179","date":"2020-05-03","county":"Stafford","state":"Virginia","cases":271,"deaths":2},{"fips":"51179","date":"2020-05-04","county":"Stafford","state":"Virginia","cases":288,"deaths":2},{"fips":"51179","date":"2020-05-05","county":"Stafford","state":"Virginia","cases":308,"deaths":2},{"fips":"51179","date":"2020-05-06","county":"Stafford","state":"Virginia","cases":308,"deaths":2},{"fips":"51179","date":"2020-05-07","county":"Stafford","state":"Virginia","cases":334,"deaths":2},{"fips":"51179","date":"2020-05-08","county":"Stafford","state":"Virginia","cases":344,"deaths":2},{"fips":"51179","date":"2020-05-09","county":"Stafford","state":"Virginia","cases":354,"deaths":2},{"fips":"51179","date":"2020-05-10","county":"Stafford","state":"Virginia","cases":374,"deaths":2},{"fips":"51179","date":"2020-05-11","county":"Stafford","state":"Virginia","cases":384,"deaths":2},{"fips":"51179","date":"2020-05-12","county":"Stafford","state":"Virginia","cases":396,"deaths":4},{"fips":"51179","date":"2020-05-13","county":"Stafford","state":"Virginia","cases":413,"deaths":4},{"fips":"51179","date":"2020-05-14","county":"Stafford","state":"Virginia","cases":426,"deaths":4},{"fips":"51179","date":"2020-05-15","county":"Stafford","state":"Virginia","cases":442,"deaths":4},{"fips":"51179","date":"2020-05-16","county":"Stafford","state":"Virginia","cases":458,"deaths":4},{"fips":"51179","date":"2020-05-17","county":"Stafford","state":"Virginia","cases":467,"deaths":4},{"fips":"51179","date":"2020-05-18","county":"Stafford","state":"Virginia","cases":484,"deaths":4},{"fips":"51179","date":"2020-05-19","county":"Stafford","state":"Virginia","cases":501,"deaths":4},{"fips":"51179","date":"2020-05-20","county":"Stafford","state":"Virginia","cases":514,"deaths":4},{"fips":"51179","date":"2020-05-21","county":"Stafford","state":"Virginia","cases":540,"deaths":4},{"fips":"51179","date":"2020-05-22","county":"Stafford","state":"Virginia","cases":552,"deaths":4},{"fips":"51179","date":"2020-05-23","county":"Stafford","state":"Virginia","cases":569,"deaths":4},{"fips":"51179","date":"2020-05-24","county":"Stafford","state":"Virginia","cases":581,"deaths":4},{"fips":"51179","date":"2020-05-25","county":"Stafford","state":"Virginia","cases":599,"deaths":4},{"fips":"51179","date":"2020-05-26","county":"Stafford","state":"Virginia","cases":642,"deaths":4},{"fips":"51179","date":"2020-05-27","county":"Stafford","state":"Virginia","cases":657,"deaths":4},{"fips":"51179","date":"2020-05-28","county":"Stafford","state":"Virginia","cases":672,"deaths":4},{"fips":"51179","date":"2020-05-29","county":"Stafford","state":"Virginia","cases":681,"deaths":4},{"fips":"51179","date":"2020-05-30","county":"Stafford","state":"Virginia","cases":702,"deaths":4},{"fips":"51179","date":"2020-05-31","county":"Stafford","state":"Virginia","cases":713,"deaths":4},{"fips":"51179","date":"2020-06-01","county":"Stafford","state":"Virginia","cases":722,"deaths":5},{"fips":"51179","date":"2020-06-02","county":"Stafford","state":"Virginia","cases":733,"deaths":5},{"fips":"51179","date":"2020-06-03","county":"Stafford","state":"Virginia","cases":738,"deaths":5},{"fips":"51179","date":"2020-06-04","county":"Stafford","state":"Virginia","cases":742,"deaths":5},{"fips":"51179","date":"2020-06-05","county":"Stafford","state":"Virginia","cases":750,"deaths":5},{"fips":"51179","date":"2020-06-06","county":"Stafford","state":"Virginia","cases":765,"deaths":5},{"fips":"51179","date":"2020-06-07","county":"Stafford","state":"Virginia","cases":803,"deaths":5},{"fips":"51179","date":"2020-06-08","county":"Stafford","state":"Virginia","cases":815,"deaths":5},{"fips":"51179","date":"2020-06-09","county":"Stafford","state":"Virginia","cases":824,"deaths":5},{"fips":"51179","date":"2020-06-10","county":"Stafford","state":"Virginia","cases":831,"deaths":5},{"fips":"51179","date":"2020-06-11","county":"Stafford","state":"Virginia","cases":841,"deaths":5},{"fips":"51179","date":"2020-06-12","county":"Stafford","state":"Virginia","cases":862,"deaths":5},{"fips":"51179","date":"2020-06-13","county":"Stafford","state":"Virginia","cases":877,"deaths":5},{"fips":"51179","date":"2020-06-14","county":"Stafford","state":"Virginia","cases":887,"deaths":5},{"fips":"51179","date":"2020-06-15","county":"Stafford","state":"Virginia","cases":893,"deaths":5},{"fips":"51179","date":"2020-06-16","county":"Stafford","state":"Virginia","cases":900,"deaths":5},{"fips":"51179","date":"2020-06-17","county":"Stafford","state":"Virginia","cases":906,"deaths":5},{"fips":"51179","date":"2020-06-18","county":"Stafford","state":"Virginia","cases":917,"deaths":5},{"fips":"51179","date":"2020-06-19","county":"Stafford","state":"Virginia","cases":921,"deaths":5},{"fips":"51179","date":"2020-06-20","county":"Stafford","state":"Virginia","cases":920,"deaths":5},{"fips":"51179","date":"2020-06-21","county":"Stafford","state":"Virginia","cases":924,"deaths":5},{"fips":"51179","date":"2020-06-22","county":"Stafford","state":"Virginia","cases":930,"deaths":5},{"fips":"51179","date":"2020-06-23","county":"Stafford","state":"Virginia","cases":936,"deaths":5},{"fips":"51179","date":"2020-06-24","county":"Stafford","state":"Virginia","cases":949,"deaths":5},{"fips":"51179","date":"2020-06-25","county":"Stafford","state":"Virginia","cases":954,"deaths":5},{"fips":"51179","date":"2020-06-26","county":"Stafford","state":"Virginia","cases":965,"deaths":5},{"fips":"51179","date":"2020-06-27","county":"Stafford","state":"Virginia","cases":974,"deaths":5},{"fips":"51179","date":"2020-06-28","county":"Stafford","state":"Virginia","cases":983,"deaths":5},{"fips":"51179","date":"2020-06-29","county":"Stafford","state":"Virginia","cases":985,"deaths":5},{"fips":"51179","date":"2020-06-30","county":"Stafford","state":"Virginia","cases":988,"deaths":5},{"fips":"51179","date":"2020-07-01","county":"Stafford","state":"Virginia","cases":990,"deaths":5},{"fips":"51179","date":"2020-07-02","county":"Stafford","state":"Virginia","cases":1000,"deaths":5},{"fips":"51179","date":"2020-07-03","county":"Stafford","state":"Virginia","cases":998,"deaths":5},{"fips":"51179","date":"2020-07-04","county":"Stafford","state":"Virginia","cases":1008,"deaths":5},{"fips":"51179","date":"2020-07-05","county":"Stafford","state":"Virginia","cases":1011,"deaths":5},{"fips":"51179","date":"2020-07-06","county":"Stafford","state":"Virginia","cases":1012,"deaths":5},{"fips":"51179","date":"2020-07-07","county":"Stafford","state":"Virginia","cases":1022,"deaths":5},{"fips":"51179","date":"2020-07-08","county":"Stafford","state":"Virginia","cases":1029,"deaths":5},{"fips":"51179","date":"2020-07-09","county":"Stafford","state":"Virginia","cases":1038,"deaths":6},{"fips":"51179","date":"2020-07-10","county":"Stafford","state":"Virginia","cases":1048,"deaths":6},{"fips":"51179","date":"2020-07-11","county":"Stafford","state":"Virginia","cases":1056,"deaths":6},{"fips":"51179","date":"2020-07-12","county":"Stafford","state":"Virginia","cases":1060,"deaths":6},{"fips":"51179","date":"2020-07-13","county":"Stafford","state":"Virginia","cases":1065,"deaths":6},{"fips":"51179","date":"2020-07-14","county":"Stafford","state":"Virginia","cases":1075,"deaths":6},{"fips":"51179","date":"2020-07-15","county":"Stafford","state":"Virginia","cases":1085,"deaths":6},{"fips":"51179","date":"2020-07-16","county":"Stafford","state":"Virginia","cases":1096,"deaths":6},{"fips":"51179","date":"2020-07-17","county":"Stafford","state":"Virginia","cases":1101,"deaths":6},{"fips":"51179","date":"2020-07-18","county":"Stafford","state":"Virginia","cases":1112,"deaths":6},{"fips":"51179","date":"2020-07-19","county":"Stafford","state":"Virginia","cases":1119,"deaths":6},{"fips":"51179","date":"2020-07-20","county":"Stafford","state":"Virginia","cases":1128,"deaths":6},{"fips":"51179","date":"2020-07-21","county":"Stafford","state":"Virginia","cases":1140,"deaths":6},{"fips":"51179","date":"2020-07-22","county":"Stafford","state":"Virginia","cases":1151,"deaths":6},{"fips":"51179","date":"2020-07-26","county":"Stafford","state":"Virginia","cases":1185,"deaths":7},{"fips":"51179","date":"2020-07-27","county":"Stafford","state":"Virginia","cases":1202,"deaths":7},{"fips":"51179","date":"2020-07-28","county":"Stafford","state":"Virginia","cases":1214,"deaths":7},{"fips":"51179","date":"2020-07-29","county":"Stafford","state":"Virginia","cases":1227,"deaths":7},{"fips":"51179","date":"2020-07-30","county":"Stafford","state":"Virginia","cases":1237,"deaths":7},{"fips":"51179","date":"2020-07-31","county":"Stafford","state":"Virginia","cases":1243,"deaths":7},{"fips":"51179","date":"2020-08-01","county":"Stafford","state":"Virginia","cases":1258,"deaths":7},{"fips":"51179","date":"2020-08-02","county":"Stafford","state":"Virginia","cases":1266,"deaths":7},{"fips":"51179","date":"2020-08-03","county":"Stafford","state":"Virginia","cases":1283,"deaths":7},{"fips":"51179","date":"2020-08-04","county":"Stafford","state":"Virginia","cases":1294,"deaths":7},{"fips":"51179","date":"2020-07-23","county":"Stafford","state":"Virginia","cases":1163,"deaths":7},{"fips":"51179","date":"2020-07-24","county":"Stafford","state":"Virginia","cases":1169,"deaths":7},{"fips":"51179","date":"2020-07-25","county":"Stafford","state":"Virginia","cases":1176,"deaths":7},{"fips":"51179","date":"2020-08-05","county":"Stafford","state":"Virginia","cases":1300,"deaths":8},{"fips":"51179","date":"2020-08-06","county":"Stafford","state":"Virginia","cases":1316,"deaths":8},{"fips":"51179","date":"2020-08-07","county":"Stafford","state":"Virginia","cases":1350,"deaths":8},{"fips":"51179","date":"2020-08-08","county":"Stafford","state":"Virginia","cases":1366,"deaths":8},{"fips":"51179","date":"2020-08-09","county":"Stafford","state":"Virginia","cases":1374,"deaths":9},{"fips":"51179","date":"2020-08-10","county":"Stafford","state":"Virginia","cases":1385,"deaths":9},{"fips":"51179","date":"2020-08-11","county":"Stafford","state":"Virginia","cases":1405,"deaths":9},{"fips":"51179","date":"2020-08-12","county":"Stafford","state":"Virginia","cases":1424,"deaths":9},{"fips":"51179","date":"2020-08-13","county":"Stafford","state":"Virginia","cases":1446,"deaths":10},{"fips":"51179","date":"2020-08-14","county":"Stafford","state":"Virginia","cases":1460,"deaths":10},{"fips":"51179","date":"2020-08-15","county":"Stafford","state":"Virginia","cases":1480,"deaths":10},{"fips":"51179","date":"2020-08-16","county":"Stafford","state":"Virginia","cases":1496,"deaths":10},{"fips":"51179","date":"2020-08-17","county":"Stafford","state":"Virginia","cases":1506,"deaths":10},{"fips":"51179","date":"2020-08-18","county":"Stafford","state":"Virginia","cases":1534,"deaths":10},{"fips":"51179","date":"2020-08-19","county":"Stafford","state":"Virginia","cases":1543,"deaths":10},{"fips":"51179","date":"2020-08-20","county":"Stafford","state":"Virginia","cases":1556,"deaths":10},{"fips":"51179","date":"2020-08-21","county":"Stafford","state":"Virginia","cases":1570,"deaths":10},{"fips":"51179","date":"2020-08-22","county":"Stafford","state":"Virginia","cases":1579,"deaths":10},{"fips":"51179","date":"2020-08-23","county":"Stafford","state":"Virginia","cases":1589,"deaths":10},{"fips":"51179","date":"2020-08-24","county":"Stafford","state":"Virginia","cases":1602,"deaths":10},{"fips":"51179","date":"2020-08-25","county":"Stafford","state":"Virginia","cases":1612,"deaths":10},{"fips":"51179","date":"2020-08-26","county":"Stafford","state":"Virginia","cases":1625,"deaths":10},{"fips":"51179","date":"2020-08-27","county":"Stafford","state":"Virginia","cases":1639,"deaths":10},{"fips":"51179","date":"2020-08-28","county":"Stafford","state":"Virginia","cases":1660,"deaths":10},{"fips":"51179","date":"2020-08-29","county":"Stafford","state":"Virginia","cases":1681,"deaths":10},{"fips":"51179","date":"2020-08-30","county":"Stafford","state":"Virginia","cases":1691,"deaths":10},{"fips":"51179","date":"2020-08-31","county":"Stafford","state":"Virginia","cases":1704,"deaths":10},{"fips":"51179","date":"2020-09-01","county":"Stafford","state":"Virginia","cases":1717,"deaths":10},{"fips":"51179","date":"2020-09-03","county":"Stafford","state":"Virginia","cases":1737,"deaths":10},{"fips":"51179","date":"2020-09-02","county":"Stafford","state":"Virginia","cases":1729,"deaths":11},{"fips":"51179","date":"2020-09-04","county":"Stafford","state":"Virginia","cases":1752,"deaths":12},{"fips":"51179","date":"2020-09-05","county":"Stafford","state":"Virginia","cases":1762,"deaths":13},{"fips":"51179","date":"2020-09-06","county":"Stafford","state":"Virginia","cases":1769,"deaths":13},{"fips":"51179","date":"2020-09-07","county":"Stafford","state":"Virginia","cases":1779,"deaths":13},{"fips":"51179","date":"2020-09-08","county":"Stafford","state":"Virginia","cases":1784,"deaths":13},{"fips":"51179","date":"2020-09-09","county":"Stafford","state":"Virginia","cases":1799,"deaths":13},{"fips":"51179","date":"2020-09-10","county":"Stafford","state":"Virginia","cases":1813,"deaths":13},{"fips":"51179","date":"2020-09-11","county":"Stafford","state":"Virginia","cases":1831,"deaths":13},{"fips":"51179","date":"2020-09-12","county":"Stafford","state":"Virginia","cases":1846,"deaths":13},{"fips":"51179","date":"2020-09-13","county":"Stafford","state":"Virginia","cases":1858,"deaths":13},{"fips":"51179","date":"2020-09-14","county":"Stafford","state":"Virginia","cases":1869,"deaths":13},{"fips":"51179","date":"2020-09-16","county":"Stafford","state":"Virginia","cases":1880,"deaths":13},{"fips":"51179","date":"2020-09-17","county":"Stafford","state":"Virginia","cases":1904,"deaths":13},{"fips":"51179","date":"2020-09-15","county":"Stafford","state":"Virginia","cases":1872,"deaths":14},{"fips":"51179","date":"2020-09-18","county":"Stafford","state":"Virginia","cases":1915,"deaths":14},{"fips":"51179","date":"2020-09-19","county":"Stafford","state":"Virginia","cases":1934,"deaths":14},{"fips":"51179","date":"2020-09-20","county":"Stafford","state":"Virginia","cases":1941,"deaths":14},{"fips":"51179","date":"2020-09-21","county":"Stafford","state":"Virginia","cases":1951,"deaths":14},{"fips":"51179","date":"2020-09-22","county":"Stafford","state":"Virginia","cases":1963,"deaths":14},{"fips":"51179","date":"2020-09-23","county":"Stafford","state":"Virginia","cases":1971,"deaths":17},{"fips":"51179","date":"2020-09-25","county":"Stafford","state":"Virginia","cases":1998,"deaths":17},{"fips":"51179","date":"2020-09-26","county":"Stafford","state":"Virginia","cases":2005,"deaths":17},{"fips":"51179","date":"2020-09-27","county":"Stafford","state":"Virginia","cases":2012,"deaths":17},{"fips":"51179","date":"2020-09-28","county":"Stafford","state":"Virginia","cases":2018,"deaths":17},{"fips":"51179","date":"2020-09-29","county":"Stafford","state":"Virginia","cases":2024,"deaths":17},{"fips":"51179","date":"2020-09-30","county":"Stafford","state":"Virginia","cases":2028,"deaths":17},{"fips":"51179","date":"2020-10-01","county":"Stafford","state":"Virginia","cases":2039,"deaths":17},{"fips":"51179","date":"2020-10-02","county":"Stafford","state":"Virginia","cases":2054,"deaths":17},{"fips":"51179","date":"2020-10-03","county":"Stafford","state":"Virginia","cases":2058,"deaths":17},{"fips":"51179","date":"2020-10-04","county":"Stafford","state":"Virginia","cases":2065,"deaths":17},{"fips":"51179","date":"2020-09-24","county":"Stafford","state":"Virginia","cases":1984,"deaths":18},{"fips":"51179","date":"2020-10-05","county":"Stafford","state":"Virginia","cases":2072,"deaths":18},{"fips":"51179","date":"2020-10-06","county":"Stafford","state":"Virginia","cases":2081,"deaths":18},{"fips":"51179","date":"2020-10-07","county":"Stafford","state":"Virginia","cases":2082,"deaths":18},{"fips":"51179","date":"2020-10-08","county":"Stafford","state":"Virginia","cases":2108,"deaths":18},{"fips":"51179","date":"2020-10-09","county":"Stafford","state":"Virginia","cases":2121,"deaths":19},{"fips":"51179","date":"2020-10-10","county":"Stafford","state":"Virginia","cases":2138,"deaths":19},{"fips":"51179","date":"2020-10-11","county":"Stafford","state":"Virginia","cases":2155,"deaths":19},{"fips":"51179","date":"2020-10-12","county":"Stafford","state":"Virginia","cases":2162,"deaths":19},{"fips":"51179","date":"2020-10-13","county":"Stafford","state":"Virginia","cases":2174,"deaths":19},{"fips":"51179","date":"2020-10-14","county":"Stafford","state":"Virginia","cases":2187,"deaths":19},{"fips":"51179","date":"2020-10-15","county":"Stafford","state":"Virginia","cases":2230,"deaths":19},{"fips":"51179","date":"2020-10-16","county":"Stafford","state":"Virginia","cases":2247,"deaths":19},{"fips":"51179","date":"2020-10-17","county":"Stafford","state":"Virginia","cases":2255,"deaths":19},{"fips":"51179","date":"2020-10-18","county":"Stafford","state":"Virginia","cases":2260,"deaths":19},{"fips":"51179","date":"2020-10-19","county":"Stafford","state":"Virginia","cases":2267,"deaths":19},{"fips":"51179","date":"2020-10-20","county":"Stafford","state":"Virginia","cases":2279,"deaths":19},{"fips":"51179","date":"2020-10-21","county":"Stafford","state":"Virginia","cases":2287,"deaths":20},{"fips":"51179","date":"2020-10-22","county":"Stafford","state":"Virginia","cases":2307,"deaths":20},{"fips":"51179","date":"2020-10-23","county":"Stafford","state":"Virginia","cases":2314,"deaths":20},{"fips":"51179","date":"2020-10-24","county":"Stafford","state":"Virginia","cases":2316,"deaths":20},{"fips":"51179","date":"2020-10-25","county":"Stafford","state":"Virginia","cases":2323,"deaths":20},{"fips":"51179","date":"2020-10-26","county":"Stafford","state":"Virginia","cases":2328,"deaths":20},{"fips":"51179","date":"2020-10-27","county":"Stafford","state":"Virginia","cases":2341,"deaths":20},{"fips":"51179","date":"2020-10-28","county":"Stafford","state":"Virginia","cases":2373,"deaths":21},{"fips":"51179","date":"2020-10-29","county":"Stafford","state":"Virginia","cases":2396,"deaths":21},{"fips":"51179","date":"2020-10-30","county":"Stafford","state":"Virginia","cases":2408,"deaths":21},{"fips":"51179","date":"2020-10-31","county":"Stafford","state":"Virginia","cases":2440,"deaths":21},{"fips":"51179","date":"2020-11-01","county":"Stafford","state":"Virginia","cases":2452,"deaths":21},{"fips":"51179","date":"2020-11-02","county":"Stafford","state":"Virginia","cases":2464,"deaths":21},{"fips":"51179","date":"2020-11-05","county":"Stafford","state":"Virginia","cases":2538,"deaths":21},{"fips":"51179","date":"2020-11-06","county":"Stafford","state":"Virginia","cases":2552,"deaths":21},{"fips":"51179","date":"2020-11-14","county":"Stafford","state":"Virginia","cases":2725,"deaths":22},{"fips":"51179","date":"2020-11-15","county":"Stafford","state":"Virginia","cases":2743,"deaths":22},{"fips":"51179","date":"2020-11-16","county":"Stafford","state":"Virginia","cases":2798,"deaths":22},{"fips":"51179","date":"2020-11-17","county":"Stafford","state":"Virginia","cases":2824,"deaths":22},{"fips":"51179","date":"2020-11-18","county":"Stafford","state":"Virginia","cases":2851,"deaths":22},{"fips":"51179","date":"2020-11-19","county":"Stafford","state":"Virginia","cases":2891,"deaths":22},{"fips":"51179","date":"2020-11-20","county":"Stafford","state":"Virginia","cases":2922,"deaths":22},{"fips":"51179","date":"2020-11-21","county":"Stafford","state":"Virginia","cases":2960,"deaths":22},{"fips":"51179","date":"2020-11-22","county":"Stafford","state":"Virginia","cases":2990,"deaths":22},{"fips":"51179","date":"2020-11-23","county":"Stafford","state":"Virginia","cases":3054,"deaths":22},{"fips":"51179","date":"2020-11-24","county":"Stafford","state":"Virginia","cases":3098,"deaths":22},{"fips":"51179","date":"2020-11-25","county":"Stafford","state":"Virginia","cases":3134,"deaths":22},{"fips":"51179","date":"2020-11-26","county":"Stafford","state":"Virginia","cases":3179,"deaths":22},{"fips":"51179","date":"2020-11-27","county":"Stafford","state":"Virginia","cases":3215,"deaths":22},{"fips":"51179","date":"2020-11-28","county":"Stafford","state":"Virginia","cases":3279,"deaths":22},{"fips":"51179","date":"2020-11-29","county":"Stafford","state":"Virginia","cases":3291,"deaths":22},{"fips":"51179","date":"2020-11-30","county":"Stafford","state":"Virginia","cases":3306,"deaths":22},{"fips":"51179","date":"2020-12-01","county":"Stafford","state":"Virginia","cases":3330,"deaths":22},{"fips":"51179","date":"2020-12-02","county":"Stafford","state":"Virginia","cases":3366,"deaths":22},{"fips":"51179","date":"2020-12-03","county":"Stafford","state":"Virginia","cases":3388,"deaths":22},{"fips":"51179","date":"2020-12-04","county":"Stafford","state":"Virginia","cases":3458,"deaths":22},{"fips":"51179","date":"2020-12-05","county":"Stafford","state":"Virginia","cases":3536,"deaths":22},{"fips":"51179","date":"2020-12-06","county":"Stafford","state":"Virginia","cases":3615,"deaths":22},{"fips":"51179","date":"2020-12-07","county":"Stafford","state":"Virginia","cases":3724,"deaths":22},{"fips":"51179","date":"2020-12-08","county":"Stafford","state":"Virginia","cases":3750,"deaths":22},{"fips":"51179","date":"2020-12-09","county":"Stafford","state":"Virginia","cases":3811,"deaths":22},{"fips":"51179","date":"2020-12-10","county":"Stafford","state":"Virginia","cases":3876,"deaths":22},{"fips":"51179","date":"2020-12-11","county":"Stafford","state":"Virginia","cases":3925,"deaths":22},{"fips":"51179","date":"2020-12-12","county":"Stafford","state":"Virginia","cases":4007,"deaths":22},{"fips":"51179","date":"2020-12-13","county":"Stafford","state":"Virginia","cases":4003,"deaths":22},{"fips":"51179","date":"2020-12-14","county":"Stafford","state":"Virginia","cases":4105,"deaths":22},{"fips":"51179","date":"2020-11-03","county":"Stafford","state":"Virginia","cases":2480,"deaths":22},{"fips":"51179","date":"2020-11-04","county":"Stafford","state":"Virginia","cases":2504,"deaths":22},{"fips":"51179","date":"2020-11-07","county":"Stafford","state":"Virginia","cases":2570,"deaths":22},{"fips":"51179","date":"2020-11-08","county":"Stafford","state":"Virginia","cases":2597,"deaths":22},{"fips":"51179","date":"2020-11-09","county":"Stafford","state":"Virginia","cases":2616,"deaths":22},{"fips":"51179","date":"2020-11-10","county":"Stafford","state":"Virginia","cases":2628,"deaths":22},{"fips":"51179","date":"2020-11-11","county":"Stafford","state":"Virginia","cases":2661,"deaths":22},{"fips":"51179","date":"2020-11-12","county":"Stafford","state":"Virginia","cases":2674,"deaths":22},{"fips":"51179","date":"2020-11-13","county":"Stafford","state":"Virginia","cases":2685,"deaths":22},{"fips":"51179","date":"2020-12-15","county":"Stafford","state":"Virginia","cases":4145,"deaths":23},{"fips":"51179","date":"2020-12-16","county":"Stafford","state":"Virginia","cases":4207,"deaths":23},{"fips":"51179","date":"2020-12-17","county":"Stafford","state":"Virginia","cases":4257,"deaths":23},{"fips":"51179","date":"2020-12-18","county":"Stafford","state":"Virginia","cases":4307,"deaths":23},{"fips":"51179","date":"2020-12-19","county":"Stafford","state":"Virginia","cases":4335,"deaths":23},{"fips":"51179","date":"2020-12-20","county":"Stafford","state":"Virginia","cases":4371,"deaths":23},{"fips":"51179","date":"2020-12-21","county":"Stafford","state":"Virginia","cases":4520,"deaths":23},{"fips":"51179","date":"2020-12-22","county":"Stafford","state":"Virginia","cases":4578,"deaths":23},{"fips":"51179","date":"2020-12-23","county":"Stafford","state":"Virginia","cases":4659,"deaths":23},{"fips":"51179","date":"2020-12-24","county":"Stafford","state":"Virginia","cases":4769,"deaths":23},{"fips":"51179","date":"2020-12-25","county":"Stafford","state":"Virginia","cases":4883,"deaths":23},{"fips":"51179","date":"2020-12-26","county":"Stafford","state":"Virginia","cases":4886,"deaths":23},{"fips":"51179","date":"2020-12-27","county":"Stafford","state":"Virginia","cases":4891,"deaths":23},{"fips":"51179","date":"2020-12-28","county":"Stafford","state":"Virginia","cases":4930,"deaths":23},{"fips":"51179","date":"2020-12-29","county":"Stafford","state":"Virginia","cases":5036,"deaths":24},{"fips":"51179","date":"2020-12-30","county":"Stafford","state":"Virginia","cases":5099,"deaths":24},{"fips":"51179","date":"2020-12-31","county":"Stafford","state":"Virginia","cases":5221,"deaths":24},{"fips":"51179","date":"2021-01-01","county":"Stafford","state":"Virginia","cases":5284,"deaths":25},{"fips":"51179","date":"2021-01-02","county":"Stafford","state":"Virginia","cases":5387,"deaths":25},{"fips":"51179","date":"2021-01-03","county":"Stafford","state":"Virginia","cases":5418,"deaths":25},{"fips":"51179","date":"2021-01-04","county":"Stafford","state":"Virginia","cases":5481,"deaths":25},{"fips":"51179","date":"2021-01-05","county":"Stafford","state":"Virginia","cases":5559,"deaths":25},{"fips":"51179","date":"2021-01-06","county":"Stafford","state":"Virginia","cases":5684,"deaths":26},{"fips":"51179","date":"2021-01-07","county":"Stafford","state":"Virginia","cases":5788,"deaths":26},{"fips":"51179","date":"2021-01-08","county":"Stafford","state":"Virginia","cases":5848,"deaths":27},{"fips":"51179","date":"2021-01-09","county":"Stafford","state":"Virginia","cases":5876,"deaths":29},{"fips":"51179","date":"2021-01-10","county":"Stafford","state":"Virginia","cases":5972,"deaths":29},{"fips":"51179","date":"2021-01-11","county":"Stafford","state":"Virginia","cases":6050,"deaths":29},{"fips":"51179","date":"2021-01-12","county":"Stafford","state":"Virginia","cases":6124,"deaths":30},{"fips":"51179","date":"2021-01-13","county":"Stafford","state":"Virginia","cases":6192,"deaths":30},{"fips":"51179","date":"2021-01-14","county":"Stafford","state":"Virginia","cases":6270,"deaths":31},{"fips":"51179","date":"2021-01-15","county":"Stafford","state":"Virginia","cases":6425,"deaths":32},{"fips":"51179","date":"2021-01-16","county":"Stafford","state":"Virginia","cases":6535,"deaths":34},{"fips":"51179","date":"2021-01-17","county":"Stafford","state":"Virginia","cases":6636,"deaths":34},{"fips":"51179","date":"2021-01-18","county":"Stafford","state":"Virginia","cases":6759,"deaths":34},{"fips":"51179","date":"2021-01-20","county":"Stafford","state":"Virginia","cases":6948,"deaths":36},{"fips":"51179","date":"2021-01-21","county":"Stafford","state":"Virginia","cases":6992,"deaths":37},{"fips":"51179","date":"2020-03-16","county":"Stafford","state":"Virginia","cases":1,"deaths":0},{"fips":"51179","date":"2020-03-17","county":"Stafford","state":"Virginia","cases":1,"deaths":0},{"fips":"51179","date":"2020-03-18","county":"Stafford","state":"Virginia","cases":2,"deaths":0},{"fips":"51179","date":"2020-03-19","county":"Stafford","state":"Virginia","cases":2,"deaths":0},{"fips":"51179","date":"2020-03-20","county":"Stafford","state":"Virginia","cases":2,"deaths":0},{"fips":"51179","date":"2020-03-21","county":"Stafford","state":"Virginia","cases":2,"deaths":0},{"fips":"51179","date":"2020-03-22","county":"Stafford","state":"Virginia","cases":5,"deaths":0},{"fips":"51179","date":"2020-03-23","county":"Stafford","state":"Virginia","cases":6,"deaths":0},{"fips":"51179","date":"2020-03-24","county":"Stafford","state":"Virginia","cases":6,"deaths":0},{"fips":"51179","date":"2020-03-25","county":"Stafford","state":"Virginia","cases":6,"deaths":0}]
