[{"state_fips_code":"37","county_fips_code":"37017","state":"North Carolina","county":"Bladen County","confirmed_cases":3124,"deaths":41,"test_7day_total":195,"positivity_7day_avg":5.64,"community":"moderate","school":"Moderate risk of transmission in schools","report_date":"2021-04-08","healthwebsites":["http://www.bladeninfo.org/departments/health"]},{"state_fips_code":"37","county_fips_code":"37017","state":"North Carolina","county":"Bladen County","confirmed_cases":3124,"deaths":41,"test_7day_total":195,"positivity_7day_avg":5.64,"community":"moderate","school":"Moderate risk of transmission in schools","report_date":"2021-04-08","healthwebsites":["http://www.bladeninfo.org/departments/health"]}]
